seatable_client/__init__.py
seatable_client/example.py
seatable_client/scripts.py
seatable_client-0.0.1.dist-info/METADATA
seatable_client-0.0.1.dist-info/WHEEL
seatable_client-0.0.1.dist-info/entry_points.txt
seatable_client-0.0.1.dist-info/top_level.txt
seatable_client-0.0.1.dist-info/RECORD
