Metadata-Version: 2.1
Name: seatable_client
Version: 0.0.1
Author: Woojin Cho
Author-email: w.cho@cj.net
License: MIT License
Requires-Python: >=3.9
Requires-Dist: click
